ecadataset/__init__.py
ecadataset/_version.py
ecadataset/dataset.py
ecadataset/scoring.py
ecadataset-0.3.4.data/scripts/ecadataset
ecadataset-0.3.4.dist-info/LICENSE
ecadataset-0.3.4.dist-info/METADATA
ecadataset-0.3.4.dist-info/WHEEL
ecadataset-0.3.4.dist-info/top_level.txt
ecadataset-0.3.4.dist-info/RECORD
