Metadata-Version: 2.1
Name: ecadataset
Version: 0.3.4
Summary: Python loader for the Endoscopic Content Area (ECA) dataset.
Home-page: https://github.com/charliebudd/eca-dataset
Author: Charlie Budd
Author-email: charles.budd@kcl.ac.uk
License: MIT
License-File: LICENSE
Requires-Dist: synapseclient
Requires-Dist: pillow
Requires-Dist: numpy
